{
  "topic": {
    "id": 59521,
    "title": "Could not complete 4 x 3.5 Minutes @ 108%",
    "fancy_title": "Could not complete 4 x 3.5 Minutes @ 108%",
    "slug": "could-not-complete-4-x-3-5-minutes-108",
    "posts_count": 11,
    "reply_count": 7,
    "highest_post_number": 11,
    "image_url": null,
    "created_at": "2025-04-26T17:16:11.187Z",
    "last_posted_at": "2025-05-05T15:42:05.492Z",
    "bumped": true,
    "bumped_at": "2025-05-05T15:42:05.492Z",
    "archetype": "regular",
    "unseen": false,
    "pinned": false,
    "unpinned": null,
    "visible": true,
    "closed": false,
    "archived": false,
    "bookmarked": null,
    "liked": null,
    "tags_descriptions": {},
    "views": 241,
    "like_count": 15,
    "has_summary": false,
    "last_poster_username": "ahmed.elsamman",
    "category_id": 9,
    "pinned_globally": false,
    "featured_link": null,
    "can_vote": false,
    "posters": [
      {
        "extras": "latest",
        "description": "Original Poster, Most Recent Poster",
        "user_id": 39728,
        "primary_group_id": null,
        "flair_group_id": null
      },
      {
        "extras": null,
        "description": "Frequent Poster",
        "user_id": 14174,
        "primary_group_id": null,
        "flair_group_id": null
      },
      {
        "extras": null,
        "description": "Frequent Poster",
        "user_id": 778,
        "primary_group_id": null,
        "flair_group_id": null
      },
      {
        "extras": null,
        "description": "Frequent Poster",
        "user_id": 4745,
        "primary_group_id": null,
        "flair_group_id": null
      },
      {
        "extras": null,
        "description": "Frequent Poster",
        "user_id": 1,
        "primary_group_id": 41,
        "flair_group_id": 41
      }
    ]
  },
  "posts": [
    {
      "id": 76409,
      "name": "ahmed.elsamman",
      "username": "ahmed.elsamman",
      "avatar_template": "/user_avatar/forums.trainerday.com/ahmed.elsamman/{size}/8844_2.png",
      "created_at": "2025-04-26T17:16:11.272Z",
      "cooked": "<p>Today I was not able to complete 4 x 3.5 Minutes @ 108%.<br>\nI finished the first two 108% intervals and wasn\u2019t able to push more in the middle of the third one.</p>\n<p>May be due to cold, fever, bad sleep, accumulated fatigue as I did VO2Max sessions on Wednesday and Thursday.</p>\n<p>But what if that due to my bad performance ?</p>\n<p>What is your recommendation in this case for better trainings and workouts ?</p>\n<p>e.g.<br>\nShould I take minutes or two and continue ?<br>\nShould I lower the FTP ?<br>\nShould I focus on HIIT sessions more than long VO2Max now ?<br>\nand So on<br>\n\u2026</p>\n<p>Your feedback are much appreciated</p>",
      "post_number": 1,
      "post_type": 1,
      "updated_at": "2025-04-26T17:16:11.272Z",
      "reply_count": 0,
      "reply_to_post_number": null,
      "quote_count": 0,
      "incoming_link_count": 12,
      "reads": 36,
      "readers_count": 35,
      "score": 67.2,
      "yours": false,
      "topic_id": 59521,
      "topic_slug": "could-not-complete-4-x-3-5-minutes-108",
      "display_username": "ahmed.elsamman",
      "primary_group_name": null,
      "flair_name": null,
      "flair_url": null,
      "flair_bg_color": null,
      "flair_color": null,
      "flair_group_id": null,
      "version": 1,
      "can_edit": false,
      "can_delete": false,
      "can_recover": false,
      "can_see_hidden_post": false,
      "can_wiki": false,
      "read": true,
      "user_title": null,
      "bookmarked": false,
      "actions_summary": [],
      "moderator": false,
      "admin": false,
      "staff": false,
      "user_id": 39728,
      "hidden": false,
      "trust_level": 2,
      "deleted_at": null,
      "user_deleted": false,
      "edit_reason": null,
      "can_view_edit_history": true,
      "wiki": false,
      "can_vote": false
    },
    {
      "id": 76417,
      "name": "dthrog00",
      "username": "dthrog00",
      "avatar_template": "/user_avatar/forums.trainerday.com/dthrog00/{size}/5002_2.png",
      "created_at": "2025-04-26T22:34:49.378Z",
      "cooked": "<p>Ahmed,</p>\n<p>What is your training background and how did you identify your FTP?  Have you successfully completed workouts similar to 4 x 3.5 minutes at 108% previously?</p>\n<p>Dave</p>",
      "post_number": 2,
      "post_type": 1,
      "updated_at": "2025-04-26T22:34:49.378Z",
      "reply_count": 1,
      "reply_to_post_number": null,
      "quote_count": 0,
      "incoming_link_count": 0,
      "reads": 36,
      "readers_count": 35,
      "score": 27.2,
      "yours": false,
      "topic_id": 59521,
      "topic_slug": "could-not-complete-4-x-3-5-minutes-108",
      "display_username": "dthrog00",
      "primary_group_name": null,
      "flair_name": null,
      "flair_url": null,
      "flair_bg_color": null,
      "flair_color": null,
      "flair_group_id": null,
      "version": 1,
      "can_edit": false,
      "can_delete": false,
      "can_recover": false,
      "can_see_hidden_post": false,
      "can_wiki": false,
      "read": true,
      "user_title": null,
      "bookmarked": false,
      "actions_summary": [
        {
          "id": 2,
          "count": 1
        }
      ],
      "moderator": false,
      "admin": false,
      "staff": false,
      "user_id": 14174,
      "hidden": false,
      "trust_level": 2,
      "deleted_at": null,
      "user_deleted": false,
      "edit_reason": null,
      "can_view_edit_history": true,
      "wiki": false
    },
    {
      "id": 76422,
      "name": "ahmed.elsamman",
      "username": "ahmed.elsamman",
      "avatar_template": "/user_avatar/forums.trainerday.com/ahmed.elsamman/{size}/8844_2.png",
      "created_at": "2025-04-26T23:46:33.803Z",
      "cooked": "<p>Hello Dave</p>\n<p>Yes I was able before even to complete at least 3x8minutes <span class=\"mention\">@108</span></p>\n<p>I far from training for too long time which decreased my FTP at least from 250W to 195W</p>\n<p>I have DiretoXR direct drive trainer and I do ramp test from time to time to determine my FTP</p>",
      "post_number": 3,
      "post_type": 1,
      "updated_at": "2025-04-27T11:44:29.643Z",
      "reply_count": 1,
      "reply_to_post_number": 2,
      "quote_count": 0,
      "incoming_link_count": 0,
      "reads": 35,
      "readers_count": 34,
      "score": 12.0,
      "yours": false,
      "topic_id": 59521,
      "topic_slug": "could-not-complete-4-x-3-5-minutes-108",
      "display_username": "ahmed.elsamman",
      "primary_group_name": null,
      "flair_name": null,
      "flair_url": null,
      "flair_bg_color": null,
      "flair_color": null,
      "flair_group_id": null,
      "version": 2,
      "can_edit": false,
      "can_delete": false,
      "can_recover": false,
      "can_see_hidden_post": false,
      "can_wiki": false,
      "read": true,
      "user_title": null,
      "reply_to_user": {
        "username": "dthrog00",
        "name": "dthrog00",
        "avatar_template": "/user_avatar/forums.trainerday.com/dthrog00/{size}/5002_2.png"
      },
      "bookmarked": false,
      "actions_summary": [],
      "moderator": false,
      "admin": false,
      "staff": false,
      "user_id": 39728,
      "hidden": false,
      "trust_level": 2,
      "deleted_at": null,
      "user_deleted": false,
      "edit_reason": null,
      "can_view_edit_history": true,
      "wiki": false
    },
    {
      "id": 76425,
      "name": "dthrog00",
      "username": "dthrog00",
      "avatar_template": "/user_avatar/forums.trainerday.com/dthrog00/{size}/5002_2.png",
      "created_at": "2025-04-27T03:32:52.261Z",
      "cooked": "<p>It is great you\u2019ve able to do 3x8\u2019s at 108%.  4x3.5 at 108% should be much easier by comparison.  You said you did back-to-back VO2 workouts on Wednesday/Thursday, I would guess that is the reason why.</p>\n<p>Maybe try it again when you are recovered?  It sounds like you are able to do the workouts when you are feeling better so the FTP should be close enough.</p>\n<p>Dave</p>",
      "post_number": 4,
      "post_type": 1,
      "updated_at": "2025-04-27T03:32:52.261Z",
      "reply_count": 0,
      "reply_to_post_number": 3,
      "quote_count": 0,
      "incoming_link_count": 1,
      "reads": 33,
      "readers_count": 32,
      "score": 26.6,
      "yours": false,
      "topic_id": 59521,
      "topic_slug": "could-not-complete-4-x-3-5-minutes-108",
      "display_username": "dthrog00",
      "primary_group_name": null,
      "flair_name": null,
      "flair_url": null,
      "flair_bg_color": null,
      "flair_color": null,
      "flair_group_id": null,
      "version": 1,
      "can_edit": false,
      "can_delete": false,
      "can_recover": false,
      "can_see_hidden_post": false,
      "can_wiki": false,
      "read": true,
      "user_title": null,
      "reply_to_user": {
        "username": "ahmed.elsamman",
        "name": "ahmed.elsamman",
        "avatar_template": "/user_avatar/forums.trainerday.com/ahmed.elsamman/{size}/8844_2.png"
      },
      "bookmarked": false,
      "actions_summary": [
        {
          "id": 2,
          "count": 1
        }
      ],
      "moderator": false,
      "admin": false,
      "staff": false,
      "user_id": 14174,
      "hidden": false,
      "trust_level": 2,
      "deleted_at": null,
      "user_deleted": false,
      "edit_reason": null,
      "can_view_edit_history": true,
      "wiki": false
    },
    {
      "id": 76439,
      "name": "",
      "username": "Alex",
      "avatar_template": "/user_avatar/forums.trainerday.com/alex/{size}/1331_2.png",
      "created_at": "2025-04-27T12:22:32.081Z",
      "cooked": "<p>Without a longer ftp test it\u2019s hard to say if ftp is good but for sure there can be some independence between anaerobic work capacity and ftp.  So a few months of hard training and your anaerobic can be at full capacity relative to your ftp. I would just reduce the number of intervals or increase rest duration but hard to say if that is best for you.</p>",
      "post_number": 5,
      "post_type": 1,
      "updated_at": "2025-04-27T12:22:32.081Z",
      "reply_count": 0,
      "reply_to_post_number": null,
      "quote_count": 0,
      "incoming_link_count": 0,
      "reads": 34,
      "readers_count": 33,
      "score": 21.8,
      "yours": false,
      "topic_id": 59521,
      "topic_slug": "could-not-complete-4-x-3-5-minutes-108",
      "display_username": "",
      "primary_group_name": "English",
      "flair_name": "English",
      "flair_url": null,
      "flair_bg_color": "",
      "flair_color": "",
      "flair_group_id": 41,
      "version": 1,
      "can_edit": false,
      "can_delete": false,
      "can_recover": false,
      "can_see_hidden_post": false,
      "can_wiki": false,
      "read": true,
      "user_title": "",
      "bookmarked": false,
      "actions_summary": [
        {
          "id": 2,
          "count": 1
        }
      ],
      "moderator": false,
      "admin": true,
      "staff": true,
      "user_id": 1,
      "hidden": false,
      "trust_level": 4,
      "deleted_at": null,
      "user_deleted": false,
      "edit_reason": null,
      "can_view_edit_history": true,
      "wiki": false
    },
    {
      "id": 76546,
      "name": "Robert UCL",
      "username": "Robert_UCL",
      "avatar_template": "/user_avatar/forums.trainerday.com/robert_ucl/{size}/1372_2.png",
      "created_at": "2025-04-28T12:19:31.663Z",
      "cooked": "<p>Am I the only one who reads that this is his third VO2max session in 4 days!?</p>\n<p>If I read your post correctly, <a class=\"mention\" href=\"/u/ahmed.elsamman\">@ahmed.elsamman</a>, you say that you have been doing Vo2 max sessions on Wednesday and Thursday, and now you say you can\u2019t finish your session of today, the 26th of April, which is Saturday.</p>\n<p>If that is truly the case, then that is the reason why you didn\u2019t finish your session.</p>\n<p>My advice is to never do two high-intensity interval sessions on consecutive days.<br>\nNext, no more than two high-intensity interval sessions per week.<br>\nThird, 3,5 minute intervals are only for the peak period in your schedule, followed by a race or end goal. It is much more effective to do shorter intervals, like 30/15\u2019s or 1/1\u2019s.<br>\nFinally, I would mix up the zones. When I create a schedule there is only one vo2max session a week. The other hiit session might be a threshold or sprint session.</p>\n<p>Hope that helps.</p>",
      "post_number": 6,
      "post_type": 1,
      "updated_at": "2025-04-28T12:26:27.086Z",
      "reply_count": 2,
      "reply_to_post_number": null,
      "quote_count": 0,
      "incoming_link_count": 3,
      "reads": 31,
      "readers_count": 30,
      "score": 61.2,
      "yours": false,
      "topic_id": 59521,
      "topic_slug": "could-not-complete-4-x-3-5-minutes-108",
      "display_username": "Robert UCL",
      "primary_group_name": null,
      "flair_name": null,
      "flair_url": null,
      "flair_bg_color": null,
      "flair_color": null,
      "flair_group_id": null,
      "version": 2,
      "can_edit": false,
      "can_delete": false,
      "can_recover": false,
      "can_see_hidden_post": false,
      "can_wiki": false,
      "read": true,
      "user_title": null,
      "bookmarked": false,
      "actions_summary": [
        {
          "id": 2,
          "count": 2
        }
      ],
      "moderator": false,
      "admin": false,
      "staff": false,
      "user_id": 778,
      "hidden": false,
      "trust_level": 4,
      "deleted_at": null,
      "user_deleted": false,
      "edit_reason": null,
      "can_view_edit_history": true,
      "wiki": false
    },
    {
      "id": 76793,
      "name": "Bad Santa",
      "username": "Bad_Santa",
      "avatar_template": "/letter_avatar_proxy/v4/letter/b/a3d4f5/{size}.png",
      "created_at": "2025-05-03T09:38:59.673Z",
      "cooked": "<p>Take a look at your today\u2019s TSB, if it\u2019s lower, than -20, then you need some rest. I usually start to struggle at -10\u202615, so I need a gentle ramp up, not aggressive one. And the higher you are in terms of CTL, less aggressive you should be in ramping up.</p>\n<p>Next to that, it\u2019s also recovery valleys that matter. How long are they? If they are too short, then you likely to bonk.</p>\n<p>Totally agree with Robe that 3 days of VO2 without a break is insane, never do that. If you are about sort of general fitness, combine in a week one SST, one Threshold and one VO2 session, all the rest is either Z2, recovery or days off.</p>\n<p>Hope, this helps.</p>",
      "post_number": 7,
      "post_type": 1,
      "updated_at": "2025-05-03T09:38:59.673Z",
      "reply_count": 1,
      "reply_to_post_number": 6,
      "quote_count": 0,
      "incoming_link_count": 1,
      "reads": 23,
      "readers_count": 22,
      "score": 44.6,
      "yours": false,
      "topic_id": 59521,
      "topic_slug": "could-not-complete-4-x-3-5-minutes-108",
      "display_username": "Bad Santa",
      "primary_group_name": null,
      "flair_name": null,
      "flair_url": null,
      "flair_bg_color": null,
      "flair_color": null,
      "flair_group_id": null,
      "version": 1,
      "can_edit": false,
      "can_delete": false,
      "can_recover": false,
      "can_see_hidden_post": false,
      "can_wiki": false,
      "read": true,
      "user_title": null,
      "reply_to_user": {
        "username": "Robert_UCL",
        "name": "Robert UCL",
        "avatar_template": "/user_avatar/forums.trainerday.com/robert_ucl/{size}/1372_2.png"
      },
      "bookmarked": false,
      "actions_summary": [
        {
          "id": 2,
          "count": 2
        }
      ],
      "moderator": false,
      "admin": false,
      "staff": false,
      "user_id": 4745,
      "hidden": false,
      "trust_level": 2,
      "deleted_at": null,
      "user_deleted": false,
      "edit_reason": null,
      "can_view_edit_history": true,
      "wiki": false
    },
    {
      "id": 76915,
      "name": "ahmed.elsamman",
      "username": "ahmed.elsamman",
      "avatar_template": "/user_avatar/forums.trainerday.com/ahmed.elsamman/{size}/8844_2.png",
      "created_at": "2025-05-05T15:03:40.599Z",
      "cooked": "<p>Hello Robert,</p>\n<p>I\u2019m always find great understanding and deep experience in your replies.</p>\n<p>Every word you write counts.</p>\n<p>Thanks a lot for your advices. I\u2019m really considered your advices.</p>\n<ol>\n<li>Never do more than two high intensity workouts per week.</li>\n<li>Never do them in two consecutive days.</li>\n<li>Do 30/30 1/1 and only do 3-5 minutes in the peak before an event.</li>\n</ol>\n<p>I\u2019m really appreciate your advices and I\u2019m going to stick to it.</p>",
      "post_number": 8,
      "post_type": 1,
      "updated_at": "2025-05-05T15:03:40.599Z",
      "reply_count": 0,
      "reply_to_post_number": 6,
      "quote_count": 0,
      "incoming_link_count": 3,
      "reads": 17,
      "readers_count": 16,
      "score": 33.4,
      "yours": false,
      "topic_id": 59521,
      "topic_slug": "could-not-complete-4-x-3-5-minutes-108",
      "display_username": "ahmed.elsamman",
      "primary_group_name": null,
      "flair_name": null,
      "flair_url": null,
      "flair_bg_color": null,
      "flair_color": null,
      "flair_group_id": null,
      "version": 1,
      "can_edit": false,
      "can_delete": false,
      "can_recover": false,
      "can_see_hidden_post": false,
      "can_wiki": false,
      "read": true,
      "user_title": null,
      "reply_to_user": {
        "username": "Robert_UCL",
        "name": "Robert UCL",
        "avatar_template": "/user_avatar/forums.trainerday.com/robert_ucl/{size}/1372_2.png"
      },
      "bookmarked": false,
      "actions_summary": [
        {
          "id": 2,
          "count": 1
        }
      ],
      "moderator": false,
      "admin": false,
      "staff": false,
      "user_id": 39728,
      "hidden": false,
      "trust_level": 2,
      "deleted_at": null,
      "user_deleted": false,
      "edit_reason": null,
      "can_view_edit_history": true,
      "wiki": false
    },
    {
      "id": 76916,
      "name": "ahmed.elsamman",
      "username": "ahmed.elsamman",
      "avatar_template": "/user_avatar/forums.trainerday.com/ahmed.elsamman/{size}/8844_2.png",
      "created_at": "2025-05-05T15:05:57.984Z",
      "cooked": "<p>This also a great advice I\u2019m going to always keep my eye on TSB. Thanks a lot.</p>",
      "post_number": 9,
      "post_type": 1,
      "updated_at": "2025-05-05T15:05:57.984Z",
      "reply_count": 1,
      "reply_to_post_number": 7,
      "quote_count": 0,
      "incoming_link_count": 1,
      "reads": 16,
      "readers_count": 15,
      "score": 43.2,
      "yours": false,
      "topic_id": 59521,
      "topic_slug": "could-not-complete-4-x-3-5-minutes-108",
      "display_username": "ahmed.elsamman",
      "primary_group_name": null,
      "flair_name": null,
      "flair_url": null,
      "flair_bg_color": null,
      "flair_color": null,
      "flair_group_id": null,
      "version": 1,
      "can_edit": false,
      "can_delete": false,
      "can_recover": false,
      "can_see_hidden_post": false,
      "can_wiki": false,
      "read": true,
      "user_title": null,
      "reply_to_user": {
        "username": "Bad_Santa",
        "name": "Bad Santa",
        "avatar_template": "/letter_avatar_proxy/v4/letter/b/a3d4f5/{size}.png"
      },
      "bookmarked": false,
      "actions_summary": [
        {
          "id": 2,
          "count": 2
        }
      ],
      "moderator": false,
      "admin": false,
      "staff": false,
      "user_id": 39728,
      "hidden": false,
      "trust_level": 2,
      "deleted_at": null,
      "user_deleted": false,
      "edit_reason": null,
      "can_view_edit_history": true,
      "wiki": false
    },
    {
      "id": 76917,
      "name": "",
      "username": "Alex",
      "avatar_template": "/user_avatar/forums.trainerday.com/alex/{size}/1331_2.png",
      "created_at": "2025-05-05T15:12:50.700Z",
      "cooked": "<p>Yes, learn to understand your TSB and how you feel and how your body is responding.  If you can track HRV and compare it to TSB it can help give clues.  With cycling some people can handle longer periods of deeper negative TSB than running for example.  So you might be able to handle -20 for a week or it might be as soon as you get to -20 you start to feel small pains or start sleeping worse, HRV drops a bunch\u2026 It\u2019s very individual and negative TSB based on volume of low intensity can frequently be tolerated better than high intensity reasons for low TSB.  So get a feel for how you react to TSB.</p>",
      "post_number": 10,
      "post_type": 1,
      "updated_at": "2025-05-05T15:12:50.700Z",
      "reply_count": 1,
      "reply_to_post_number": 9,
      "quote_count": 0,
      "incoming_link_count": 0,
      "reads": 15,
      "readers_count": 14,
      "score": 53.0,
      "yours": false,
      "topic_id": 59521,
      "topic_slug": "could-not-complete-4-x-3-5-minutes-108",
      "display_username": "",
      "primary_group_name": "English",
      "flair_name": "English",
      "flair_url": null,
      "flair_bg_color": "",
      "flair_color": "",
      "flair_group_id": 41,
      "version": 1,
      "can_edit": false,
      "can_delete": false,
      "can_recover": false,
      "can_see_hidden_post": false,
      "can_wiki": false,
      "read": true,
      "user_title": "",
      "reply_to_user": {
        "username": "ahmed.elsamman",
        "name": "ahmed.elsamman",
        "avatar_template": "/user_avatar/forums.trainerday.com/ahmed.elsamman/{size}/8844_2.png"
      },
      "bookmarked": false,
      "actions_summary": [
        {
          "id": 2,
          "count": 3
        }
      ],
      "moderator": false,
      "admin": true,
      "staff": true,
      "user_id": 1,
      "hidden": false,
      "trust_level": 4,
      "deleted_at": null,
      "user_deleted": false,
      "edit_reason": null,
      "can_view_edit_history": true,
      "wiki": false
    },
    {
      "id": 76919,
      "name": "ahmed.elsamman",
      "username": "ahmed.elsamman",
      "avatar_template": "/user_avatar/forums.trainerday.com/ahmed.elsamman/{size}/8844_2.png",
      "created_at": "2025-05-05T15:42:05.492Z",
      "cooked": "<p>Thanks a lot Alex for the detailed information.<br>\nYour words always count.</p>\n<p>I\u2019m going to observe my HRV with TSB<br>\nI got your point about TSB may be more or less tolerated according to volume and intensity.</p>",
      "post_number": 11,
      "post_type": 1,
      "updated_at": "2025-05-05T15:43:57.637Z",
      "reply_count": 0,
      "reply_to_post_number": 10,
      "quote_count": 0,
      "incoming_link_count": 0,
      "reads": 15,
      "readers_count": 14,
      "score": 63.0,
      "yours": false,
      "topic_id": 59521,
      "topic_slug": "could-not-complete-4-x-3-5-minutes-108",
      "display_username": "ahmed.elsamman",
      "primary_group_name": null,
      "flair_name": null,
      "flair_url": null,
      "flair_bg_color": null,
      "flair_color": null,
      "flair_group_id": null,
      "version": 1,
      "can_edit": false,
      "can_delete": false,
      "can_recover": false,
      "can_see_hidden_post": false,
      "can_wiki": false,
      "read": true,
      "user_title": null,
      "reply_to_user": {
        "username": "Alex",
        "name": "",
        "avatar_template": "/user_avatar/forums.trainerday.com/alex/{size}/1331_2.png"
      },
      "bookmarked": false,
      "actions_summary": [
        {
          "id": 2,
          "count": 2
        }
      ],
      "moderator": false,
      "admin": false,
      "staff": false,
      "user_id": 39728,
      "hidden": false,
      "trust_level": 2,
      "deleted_at": null,
      "user_deleted": false,
      "edit_reason": null,
      "can_view_edit_history": true,
      "wiki": false
    }
  ],
  "downloaded_at": "2025-06-27T06:59:59.637058"
}